cyberpy3/__init__.py
cyberpy3-0.0.3.dist-info/METADATA
cyberpy3-0.0.3.dist-info/WHEEL
cyberpy3-0.0.3.dist-info/top_level.txt
cyberpy3-0.0.3.dist-info/RECORD
