Metadata-Version: 2.1
Name: cyberpy3
Version: 0.0.3
Summary: library for cyber pi
Home-page: https://makeblock.com
Author: makeblock
Author-email: flashindream@gmail.com
License: UNKNOWN
Platform: UNKNOWN
Requires-Dist: makeblock
